{
  "_links": {
    "self": {
      "href": "https://us.api.blizzard.com/data/wow/connected-realm/5/mythic-leaderboard/?namespace=dynamic-us"
    }
  },
  "current_leaderboards": [
    {
      "key": {
        "href": "https://us.api.blizzard.com/data/wow/connected-realm/5/mythic-leaderboard/2/period/894?namespace=dynamic-us"
      },
      "name": "Temple of the Jade Serpent",
      "id": 2
    },
    {
      "key": {
        "href": "https://us.api.blizzard.com/data/wow/connected-realm/5/mythic-leaderboard/165/period/894?namespace=dynamic-us"
      },
      "name": "Shadowmoon Burial Grounds",
      "id": 165
    },
    {
      "key": {
        "href": "https://us.api.blizzard.com/data/wow/connected-realm/5/mythic-leaderboard/200/period/894?namespace=dynamic-us"
      },
      "name": "Halls of Valor",
      "id": 200
    },
    {
      "key": {
        "href": "https://us.api.blizzard.com/data/wow/connected-realm/5/mythic-leaderboard/210/period/894?namespace=dynamic-us"
      },
      "name": "Court of Stars",
      "id": 210
    },
    {
      "key": {
        "href": "https://us.api.blizzard.com/data/wow/connected-realm/5/mythic-leaderboard/399/period/894?namespace=dynamic-us"
      },
      "name": "Ruby Life Pools",
      "id": 399
    },
    {
      "key": {
        "href": "https://us.api.blizzard.com/data/wow/connected-realm/5/mythic-leaderboard/400/period/894?namespace=dynamic-us"
      },
      "name": "The Nokhud Offensive",
      "id": 400
    },
    {
      "key": {
        "href": "https://us.api.blizzard.com/data/wow/connected-realm/5/mythic-leaderboard/401/period/894?namespace=dynamic-us"
      },
      "name": "The Azure Vault",
      "id": 401
    },
    {
      "key": {
        "href": "https://us.api.blizzard.com/data/wow/connected-realm/5/mythic-leaderboard/402/period/894?namespace=dynamic-us"
      },
      "name": "Algeth'ar Academy",
      "id": 402
    }
  ]
}
